nbdev_tutorial/__init__.py
nbdev_tutorial/_nbdev.py
nbdev_tutorial/core.py
nbdev_tutorial_vb/__init__.py
nbdev_tutorial_vb/_nbdev.py
nbdev_tutorial_vb/core.py
nbdev_tutorial_vb-0.0.2.dist-info/LICENSE
nbdev_tutorial_vb-0.0.2.dist-info/METADATA
nbdev_tutorial_vb-0.0.2.dist-info/WHEEL
nbdev_tutorial_vb-0.0.2.dist-info/entry_points.txt
nbdev_tutorial_vb-0.0.2.dist-info/top_level.txt
nbdev_tutorial_vb-0.0.2.dist-info/RECORD
