Metadata-Version: 2.1
Name: nbdev-tutorial-vb
Version: 0.0.2
Summary: A tutorial project for nbdev
Home-page: https://github.com/vishalbakshi/nbdev_tutorial_vb/tree/master/
Author: Vishal Bakshi
Author-email: vdbakshi@gmail.com
License: Apache Software License 2.0
Keywords: fastai,nbdev
Platform: UNKNOWN
Classifier: Development Status :: 3 - Alpha
Classifier: Intended Audience :: Developers
Classifier: License :: OSI Approved :: Apache Software License
Classifier: Natural Language :: English
Classifier: Programming Language :: Python :: 3.6
Classifier: Programming Language :: Python :: 3.7
Classifier: Programming Language :: Python :: 3.8
Requires-Python: >=3.6
Requires-Dist: fastcore
